vtgui/__init__.py
vtgui/app.py
vtgui/fields.py
vtgui/gui.py
vtgui/utils.py
vtgui-0.0.0.9.dist-info/LICENSE
vtgui-0.0.0.9.dist-info/METADATA
vtgui-0.0.0.9.dist-info/WHEEL
vtgui-0.0.0.9.dist-info/entry_points.txt
vtgui-0.0.0.9.dist-info/top_level.txt
vtgui-0.0.0.9.dist-info/RECORD
