Metadata-Version: 2.1
Name: vtgui
Version: 0.0.0.9
Summary: vtgui is a wrapper for pyqt5
Home-page: http://github.com/Peiiii/vtgui
Author: Wang Pei
Author-email: 1535376447@qq.com
License: UNKNOWN
Platform: UNKNOWN
Classifier: Programming Language :: Python :: 3
Classifier: License :: OSI Approved :: MIT License
Classifier: Operating System :: OS Independent
Requires-Python: >=3.0
Requires-Dist: pyqt5
Requires-Dist: wpkit2
